import_export_celery/__init__.py
import_export_celery/admin.py
import_export_celery/admin_actions.py
import_export_celery/apps.py
import_export_celery/fields.py
import_export_celery/model_config.py
import_export_celery/tasks.py
import_export_celery/utils.py
import_export_celery/locale/pt/LC_MESSAGES/django.mo
import_export_celery/migrations/0001_initial.py
import_export_celery/migrations/0002_auto_20190923_1132.py
import_export_celery/migrations/0003_exportjob.py
import_export_celery/migrations/0004_exportjob_email_on_completion.py
import_export_celery/migrations/0005_exportjob_site_of_origin.py
import_export_celery/migrations/0006_auto_20191125_1236.py
import_export_celery/migrations/0007_auto_20210210_1831.py
import_export_celery/migrations/0008_alter_exportjob_id_alter_importjob_id.py
import_export_celery/migrations/0009_alter_exportjob_options_alter_importjob_options_and_more.py
import_export_celery/migrations/0010_auto_20231013_0904.py
import_export_celery/migrations/__init__.py
import_export_celery/models/__init__.py
import_export_celery/models/exportjob.py
import_export_celery/models/importjob.py
import_export_celery/templates/email/export_job_completion.html
django_import_export_celery-1.7.1.dist-info/LICENSE
django_import_export_celery-1.7.1.dist-info/METADATA
django_import_export_celery-1.7.1.dist-info/WHEEL
django_import_export_celery-1.7.1.dist-info/top_level.txt
django_import_export_celery-1.7.1.dist-info/RECORD
