Metadata-Version: 2.1
Name: django-import-export-celery
Version: 1.7.1
Summary: Process long running django imports and exports in celery
Home-page: https://github.com/auto-mat/django-import-export-celery
Download-URL: http://pypi.python.org/pypi/django-import-export-celery/
Author: Timothy Hobbs
Author-email: timothy.hobbs@auto-mat.cz
License: License :: OSI Approved :: GNU Lesser General Public License v3.0 or later (LGPLv3.0+)
Classifier: Topic :: Utilities
Classifier: Natural Language :: English
Classifier: Operating System :: OS Independent
Classifier: Intended Audience :: Developers
Classifier: Environment :: Web Environment
Classifier: Framework :: Django
Classifier: Programming Language :: Python :: 3.7
Classifier: Programming Language :: Python :: 3.8
Classifier: Programming Language :: Python :: 3.9
License-File: LICENSE
Requires-Dist: Django
Requires-Dist: django-import-export
Requires-Dist: django-author
Requires-Dist: html2text
